asyncml/__init__.py
asyncml/base.py
asyncml-0.0.1.dist-info/LICENSE
asyncml-0.0.1.dist-info/METADATA
asyncml-0.0.1.dist-info/WHEEL
asyncml-0.0.1.dist-info/top_level.txt
asyncml-0.0.1.dist-info/RECORD
